xrmreader/__init__.py
xrmreader/preprocessor.py
xrmreader/reader.py
xrmreader-2.9.1.dist-info/LICENSE
xrmreader-2.9.1.dist-info/METADATA
xrmreader-2.9.1.dist-info/WHEEL
xrmreader-2.9.1.dist-info/top_level.txt
xrmreader-2.9.1.dist-info/RECORD
