Metadata-Version: 2.1
Name: xrmreader
Version: 2.9.1
Summary: A reader and preprocessor for txrm/xrm data acquired by Zeiss microscopes.
Home-page: https://git5.cs.fau.de/mthies/xrm_reader
Author: Mareike Thies
Author-email: mareike.thies@fau.de
Classifier: Programming Language :: Python :: 3
Classifier: Operating System :: OS Independent
Requires-Python: >=3.6
License-File: LICENSE
Requires-Dist: numpy
Requires-Dist: scipy
Requires-Dist: olefile
Requires-Dist: scikit-image
Requires-Dist: tqdm
